barbud/__init__.py
barbud/main.py
barbud/services.py
barbud/digits/__init__.py
barbud-0.1.0.dist-info/METADATA
barbud-0.1.0.dist-info/WHEEL
barbud-0.1.0.dist-info/top_level.txt
barbud-0.1.0.dist-info/RECORD
