Metadata-Version: 2.1
Name: barbud
Version: 0.1.0
Summary: Barcode Tool
Author: Marc Work
Requires-Dist: click==8.1.7
